wtforms_alchemy/__init__.py
wtforms_alchemy/exc.py
wtforms_alchemy/fields.py
wtforms_alchemy/generator.py
wtforms_alchemy/utils.py
wtforms_alchemy/validators.py
marvin_wtforms_alchemy-0.18.0.dist-info/LICENSE
marvin_wtforms_alchemy-0.18.0.dist-info/METADATA
marvin_wtforms_alchemy-0.18.0.dist-info/WHEEL
marvin_wtforms_alchemy-0.18.0.dist-info/top_level.txt
marvin_wtforms_alchemy-0.18.0.dist-info/RECORD
